[
    {
      "inputs": [],
      "stateMutability": "nonpayable",
      "type": "constructor"
    },
    {
      "inputs": [],
      "name": "ECDSAInvalidSignature",
      "type": "error"
    },
    {
      "inputs": [
        {
          "internalType": "uint256",
          "name": "length",
          "type": "uint256"
        }
      ],
      "name": "ECDSAInvalidSignatureLength",
      "type": "error"
    },
    {
      "inputs": [
        {
          "internalType": "bytes32",
          "name": "s",
          "type": "bytes32"
        }
      ],
      "name": "ECDSAInvalidSignatureS",
      "type": "error"
    },
    {
      "inputs": [],
      "name": "ReentrancyGuardReentrantCall",
      "type": "error"
    },
    {
      "anonymous": false,
      "inputs": [
        {
          "indexed": true,
          "internalType": "uint8",
          "name": "tierId",
          "type": "uint8"
        },
        {
          "indexed": true,
          "internalType": "uint8",
          "name": "instanceId",
          "type": "uint8"
        },
        {
          "indexed": false,
          "internalType": "uint8",
          "name": "roundNumber",
          "type": "uint8"
        },
        {
          "indexed": false,
          "internalType": "uint8",
          "name": "remainingPlayers",
          "type": "uint8"
        }
      ],
      "name": "AllDrawRoundDetected",
      "type": "event"
    },
    {
      "anonymous": false,
      "inputs": [
        {
          "indexed": true,
          "internalType": "bytes32",
          "name": "matchId",
          "type": "bytes32"
        },
        {
          "indexed": true,
          "internalType": "address",
          "name": "winner",
          "type": "address"
        },
        {
          "indexed": true,
          "internalType": "address",
          "name": "loser",
          "type": "address"
        }
      ],
      "name": "AllShipsSunk",
      "type": "event"
    },
    {
      "anonymous": false,
      "inputs": [
        {
          "indexed": true,
          "internalType": "bytes32",
          "name": "matchKey",
          "type": "bytes32"
        },
        {
          "indexed": false,
          "internalType": "uint16",
          "name": "cacheIndex",
          "type": "uint16"
        },
        {
          "indexed": true,
          "internalType": "address",
          "name": "player1",
          "type": "address"
        },
        {
          "indexed": true,
          "internalType": "address",
          "name": "player2",
          "type": "address"
        }
      ],
      "name": "BattleshipMatchCached",
      "type": "event"
    },
    {
      "anonymous": false,
      "inputs": [
        {
          "indexed": true,
          "internalType": "bytes32",
          "name": "matchId",
          "type": "bytes32"
        },
        {
          "indexed": true,
          "internalType": "address",
          "name": "player",
          "type": "address"
        }
      ],
      "name": "BoardCommitted",
      "type": "event"
    },
    {
      "anonymous": false,
      "inputs": [
        {
          "indexed": true,
          "internalType": "bytes32",
          "name": "matchId",
          "type": "bytes32"
        },
        {
          "indexed": true,
          "internalType": "address",
          "name": "player",
          "type": "address"
        }
      ],
      "name": "BoardRevealed",
      "type": "event"
    },
    {
      "anonymous": false,
      "inputs": [
        {
          "indexed": true,
          "internalType": "uint8",
          "name": "tierId",
          "type": "uint8"
        },
        {
          "indexed": true,
          "internalType": "uint8",
          "name": "instanceId",
          "type": "uint8"
        },
        {
          "indexed": true,
          "internalType": "address",
          "name": "claimant",
          "type": "address"
        },
        {
          "indexed": false,
          "internalType": "uint256",
          "name": "amount",
          "type": "uint256"
        }
      ],
      "name": "EnrollmentPoolClaimed",
      "type": "event"
    },
    {
      "anonymous": false,
      "inputs": [
        {
          "indexed": true,
          "internalType": "bytes32",
          "name": "matchId",
          "type": "bytes32"
        },
        {
          "indexed": false,
          "internalType": "address",
          "name": "winner",
          "type": "address"
        },
        {
          "indexed": false,
          "internalType": "bool",
          "name": "isDraw",
          "type": "bool"
        }
      ],
      "name": "MatchCompleted",
      "type": "event"
    },
    {
      "anonymous": false,
      "inputs": [
        {
          "indexed": true,
          "internalType": "uint8",
          "name": "tierId",
          "type": "uint8"
        },
        {
          "indexed": true,
          "internalType": "uint8",
          "name": "instanceId",
          "type": "uint8"
        },
        {
          "indexed": false,
          "internalType": "uint8",
          "name": "roundNumber",
          "type": "uint8"
        },
        {
          "indexed": false,
          "internalType": "uint8",
          "name": "matchNumber",
          "type": "uint8"
        },
        {
          "indexed": false,
          "internalType": "address",
          "name": "player1",
          "type": "address"
        },
        {
          "indexed": false,
          "internalType": "address",
          "name": "player2",
          "type": "address"
        }
      ],
      "name": "MatchStarted",
      "type": "event"
    },
    {
      "anonymous": false,
      "inputs": [
        {
          "indexed": true,
          "internalType": "address",
          "name": "owner",
          "type": "address"
        },
        {
          "indexed": false,
          "internalType": "uint256",
          "name": "amount",
          "type": "uint256"
        }
      ],
      "name": "OwnerFeePaid",
      "type": "event"
    },
    {
      "anonymous": false,
      "inputs": [
        {
          "indexed": true,
          "internalType": "uint8",
          "name": "tierId",
          "type": "uint8"
        },
        {
          "indexed": true,
          "internalType": "uint8",
          "name": "instanceId",
          "type": "uint8"
        },
        {
          "indexed": false,
          "internalType": "uint8",
          "name": "roundNumber",
          "type": "uint8"
        },
        {
          "indexed": true,
          "internalType": "address",
          "name": "player",
          "type": "address"
        }
      ],
      "name": "PlayerAutoAdvancedWalkover",
      "type": "event"
    },
    {
      "anonymous": false,
      "inputs": [
        {
          "indexed": true,
          "internalType": "uint8",
          "name": "tierId",
          "type": "uint8"
        },
        {
          "indexed": true,
          "internalType": "uint8",
          "name": "instanceId",
          "type": "uint8"
        },
        {
          "indexed": true,
          "internalType": "address",
          "name": "player",
          "type": "address"
        },
        {
          "indexed": false,
          "internalType": "uint8",
          "name": "enrolledCount",
          "type": "uint8"
        }
      ],
      "name": "PlayerEnrolled",
      "type": "event"
    },
    {
      "anonymous": false,
      "inputs": [
        {
          "indexed": true,
          "internalType": "uint8",
          "name": "tierId",
          "type": "uint8"
        },
        {
          "indexed": true,
          "internalType": "uint8",
          "name": "instanceId",
          "type": "uint8"
        },
        {
          "indexed": true,
          "internalType": "address",
          "name": "player",
          "type": "address"
        },
        {
          "indexed": false,
          "internalType": "uint256",
          "name": "amount",
          "type": "uint256"
        },
        {
          "indexed": false,
          "internalType": "string",
          "name": "reason",
          "type": "string"
        }
      ],
      "name": "PlayerForfeited",
      "type": "event"
    },
    {
      "anonymous": false,
      "inputs": [
        {
          "indexed": true,
          "internalType": "uint8",
          "name": "tierId",
          "type": "uint8"
        },
        {
          "indexed": true,
          "internalType": "uint8",
          "name": "instanceId",
          "type": "uint8"
        },
        {
          "indexed": false,
          "internalType": "uint8",
          "name": "roundNumber",
          "type": "uint8"
        },
        {
          "indexed": false,
          "internalType": "address",
          "name": "player1",
          "type": "address"
        },
        {
          "indexed": false,
          "internalType": "address",
          "name": "player2",
          "type": "address"
        }
      ],
      "name": "PlayersConsolidated",
      "type": "event"
    },
    {
      "anonymous": false,
      "inputs": [
        {
          "indexed": true,
          "internalType": "uint8",
          "name": "tierId",
          "type": "uint8"
        },
        {
          "indexed": true,
          "internalType": "uint8",
          "name": "instanceId",
          "type": "uint8"
        },
        {
          "indexed": true,
          "internalType": "address",
          "name": "player",
          "type": "address"
        },
        {
          "indexed": false,
          "internalType": "uint8",
          "name": "rank",
          "type": "uint8"
        },
        {
          "indexed": false,
          "internalType": "uint256",
          "name": "amount",
          "type": "uint256"
        }
      ],
      "name": "PrizeDistributed",
      "type": "event"
    },
    {
      "anonymous": false,
      "inputs": [
        {
          "indexed": true,
          "internalType": "address",
          "name": "recipient",
          "type": "address"
        },
        {
          "indexed": false,
          "internalType": "uint256",
          "name": "amount",
          "type": "uint256"
        }
      ],
      "name": "ProtocolFeePaid",
      "type": "event"
    },
    {
      "anonymous": false,
      "inputs": [
        {
          "indexed": true,
          "internalType": "uint8",
          "name": "tierId",
          "type": "uint8"
        },
        {
          "indexed": true,
          "internalType": "uint8",
          "name": "instanceId",
          "type": "uint8"
        },
        {
          "indexed": false,
          "internalType": "uint8",
          "name": "roundNumber",
          "type": "uint8"
        }
      ],
      "name": "RoundCompleted",
      "type": "event"
    },
    {
      "anonymous": false,
      "inputs": [
        {
          "indexed": true,
          "internalType": "uint8",
          "name": "tierId",
          "type": "uint8"
        },
        {
          "indexed": true,
          "internalType": "uint8",
          "name": "instanceId",
          "type": "uint8"
        },
        {
          "indexed": false,
          "internalType": "uint8",
          "name": "roundNumber",
          "type": "uint8"
        },
        {
          "indexed": false,
          "internalType": "uint8",
          "name": "matchCount",
          "type": "uint8"
        }
      ],
      "name": "RoundInitialized",
      "type": "event"
    },
    {
      "anonymous": false,
      "inputs": [
        {
          "indexed": true,
          "internalType": "bytes32",
          "name": "matchId",
          "type": "bytes32"
        },
        {
          "indexed": true,
          "internalType": "address",
          "name": "shooter",
          "type": "address"
        },
        {
          "indexed": false,
          "internalType": "uint8",
          "name": "targetCell",
          "type": "uint8"
        },
        {
          "indexed": false,
          "internalType": "bool",
          "name": "isHit",
          "type": "bool"
        }
      ],
      "name": "ShotFired",
      "type": "event"
    },
    {
      "anonymous": false,
      "inputs": [
        {
          "indexed": true,
          "internalType": "uint8",
          "name": "tierId",
          "type": "uint8"
        },
        {
          "indexed": false,
          "internalType": "uint8",
          "name": "playerCount",
          "type": "uint8"
        },
        {
          "indexed": false,
          "internalType": "uint8",
          "name": "instanceCount",
          "type": "uint8"
        },
        {
          "indexed": false,
          "internalType": "uint256",
          "name": "entryFee",
          "type": "uint256"
        }
      ],
      "name": "TierRegistered",
      "type": "event"
    },
    {
      "anonymous": false,
      "inputs": [
        {
          "indexed": true,
          "internalType": "uint8",
          "name": "tierId",
          "type": "uint8"
        },
        {
          "indexed": true,
          "internalType": "uint8",
          "name": "instanceId",
          "type": "uint8"
        },
        {
          "indexed": false,
          "internalType": "uint8",
          "name": "roundNum",
          "type": "uint8"
        },
        {
          "indexed": false,
          "internalType": "uint8",
          "name": "matchNum",
          "type": "uint8"
        },
        {
          "indexed": true,
          "internalType": "address",
          "name": "winner",
          "type": "address"
        },
        {
          "indexed": false,
          "internalType": "address",
          "name": "loser",
          "type": "address"
        }
      ],
      "name": "TimeoutVictoryClaimed",
      "type": "event"
    },
    {
      "anonymous": false,
      "inputs": [
        {
          "indexed": true,
          "internalType": "uint8",
          "name": "tierId",
          "type": "uint8"
        },
        {
          "indexed": true,
          "internalType": "uint8",
          "name": "instanceId",
          "type": "uint8"
        },
        {
          "indexed": true,
          "internalType": "uint256",
          "name": "tournamentId",
          "type": "uint256"
        },
        {
          "indexed": false,
          "internalType": "address",
          "name": "winner",
          "type": "address"
        }
      ],
      "name": "TournamentCached",
      "type": "event"
    },
    {
      "anonymous": false,
      "inputs": [
        {
          "indexed": true,
          "internalType": "uint8",
          "name": "tierId",
          "type": "uint8"
        },
        {
          "indexed": true,
          "internalType": "uint8",
          "name": "instanceId",
          "type": "uint8"
        },
        {
          "indexed": false,
          "internalType": "address",
          "name": "winner",
          "type": "address"
        },
        {
          "indexed": false,
          "internalType": "uint256",
          "name": "prizeAmount",
          "type": "uint256"
        },
        {
          "indexed": false,
          "internalType": "bool",
          "name": "finalsWasDraw",
          "type": "bool"
        },
        {
          "indexed": false,
          "internalType": "address",
          "name": "coWinner",
          "type": "address"
        }
      ],
      "name": "TournamentCompleted",
      "type": "event"
    },
    {
      "anonymous": false,
      "inputs": [
        {
          "indexed": true,
          "internalType": "uint8",
          "name": "tierId",
          "type": "uint8"
        },
        {
          "indexed": true,
          "internalType": "uint8",
          "name": "instanceId",
          "type": "uint8"
        },
        {
          "indexed": false,
          "internalType": "uint8",
          "name": "roundNumber",
          "type": "uint8"
        },
        {
          "indexed": false,
          "internalType": "uint8",
          "name": "sharedWinnerCount",
          "type": "uint8"
        },
        {
          "indexed": false,
          "internalType": "uint256",
          "name": "prizePerWinner",
          "type": "uint256"
        }
      ],
      "name": "TournamentCompletedAllDraw",
      "type": "event"
    },
    {
      "anonymous": false,
      "inputs": [
        {
          "indexed": true,
          "internalType": "uint8",
          "name": "tierId",
          "type": "uint8"
        },
        {
          "indexed": true,
          "internalType": "uint8",
          "name": "instanceId",
          "type": "uint8"
        },
        {
          "indexed": true,
          "internalType": "address",
          "name": "starter",
          "type": "address"
        },
        {
          "indexed": false,
          "internalType": "uint8",
          "name": "playerCount",
          "type": "uint8"
        }
      ],
      "name": "TournamentForceStarted",
      "type": "event"
    },
    {
      "anonymous": false,
      "inputs": [
        {
          "indexed": true,
          "internalType": "uint8",
          "name": "tierId",
          "type": "uint8"
        },
        {
          "indexed": true,
          "internalType": "uint8",
          "name": "instanceId",
          "type": "uint8"
        }
      ],
      "name": "TournamentInitialized",
      "type": "event"
    },
    {
      "anonymous": false,
      "inputs": [
        {
          "indexed": true,
          "internalType": "uint8",
          "name": "tierId",
          "type": "uint8"
        },
        {
          "indexed": true,
          "internalType": "uint8",
          "name": "instanceId",
          "type": "uint8"
        }
      ],
      "name": "TournamentReset",
      "type": "event"
    },
    {
      "anonymous": false,
      "inputs": [
        {
          "indexed": true,
          "internalType": "uint8",
          "name": "tierId",
          "type": "uint8"
        },
        {
          "indexed": true,
          "internalType": "uint8",
          "name": "instanceId",
          "type": "uint8"
        },
        {
          "indexed": false,
          "internalType": "uint8",
          "name": "playerCount",
          "type": "uint8"
        }
      ],
      "name": "TournamentStarted",
      "type": "event"
    },
    {
      "inputs": [],
      "name": "BASIS_POINTS",
      "outputs": [
        {
          "internalType": "uint256",
          "name": "",
          "type": "uint256"
        }
      ],
      "stateMutability": "view",
      "type": "function"
    },
    {
      "inputs": [],
      "name": "BATTLESHIP_SIZE",
      "outputs": [
        {
          "internalType": "uint8",
          "name": "",
          "type": "uint8"
        }
      ],
      "stateMutability": "view",
      "type": "function"
    },
    {
      "inputs": [],
      "name": "BOARD_SIZE",
      "outputs": [
        {
          "internalType": "uint8",
          "name": "",
          "type": "uint8"
        }
      ],
      "stateMutability": "view",
      "type": "function"
    },
    {
      "inputs": [],
      "name": "BOARD_WIDTH",
      "outputs": [
        {
          "internalType": "uint8",
          "name": "",
          "type": "uint8"
        }
      ],
      "stateMutability": "view",
      "type": "function"
    },
    {
      "inputs": [],
      "name": "CARRIER_SIZE",
      "outputs": [
        {
          "internalType": "uint8",
          "name": "",
          "type": "uint8"
        }
      ],
      "stateMutability": "view",
      "type": "function"
    },
    {
      "inputs": [],
      "name": "CRUISER_SIZE",
      "outputs": [
        {
          "internalType": "uint8",
          "name": "",
          "type": "uint8"
        }
      ],
      "stateMutability": "view",
      "type": "function"
    },
    {
      "inputs": [],
      "name": "DEFAULT_ENROLLMENT_WINDOW",
      "outputs": [
        {
          "internalType": "uint256",
          "name": "",
          "type": "uint256"
        }
      ],
      "stateMutability": "view",
      "type": "function"
    },
    {
      "inputs": [],
      "name": "DEFAULT_ESCALATION_INTERVAL",
      "outputs": [
        {
          "internalType": "uint256",
          "name": "",
          "type": "uint256"
        }
      ],
      "stateMutability": "view",
      "type": "function"
    },
    {
      "inputs": [],
      "name": "DEFAULT_MATCH_MOVE_TIMEOUT",
      "outputs": [
        {
          "internalType": "uint256",
          "name": "",
          "type": "uint256"
        }
      ],
      "stateMutability": "view",
      "type": "function"
    },
    {
      "inputs": [],
      "name": "DESTROYER_SIZE",
      "outputs": [
        {
          "internalType": "uint8",
          "name": "",
          "type": "uint8"
        }
      ],
      "stateMutability": "view",
      "type": "function"
    },
    {
      "inputs": [
        {
          "internalType": "uint8",
          "name": "tierId",
          "type": "uint8"
        }
      ],
      "name": "ENTRY_FEES",
      "outputs": [
        {
          "internalType": "uint256",
          "name": "",
          "type": "uint256"
        }
      ],
      "stateMutability": "view",
      "type": "function"
    },
    {
      "inputs": [
        {
          "internalType": "uint8",
          "name": "tierId",
          "type": "uint8"
        }
      ],
      "name": "INSTANCE_COUNTS",
      "outputs": [
        {
          "internalType": "uint8",
          "name": "",
          "type": "uint8"
        }
      ],
      "stateMutability": "view",
      "type": "function"
    },
    {
      "inputs": [],
      "name": "MATCH_CACHE_SIZE",
      "outputs": [
        {
          "internalType": "uint16",
          "name": "",
          "type": "uint16"
        }
      ],
      "stateMutability": "view",
      "type": "function"
    },
    {
      "inputs": [],
      "name": "NO_CELL",
      "outputs": [
        {
          "internalType": "uint8",
          "name": "",
          "type": "uint8"
        }
      ],
      "stateMutability": "view",
      "type": "function"
    },
    {
      "inputs": [],
      "name": "NO_ROUND",
      "outputs": [
        {
          "internalType": "uint8",
          "name": "",
          "type": "uint8"
        }
      ],
      "stateMutability": "view",
      "type": "function"
    },
    {
      "inputs": [],
      "name": "OWNER_SHARE_BPS",
      "outputs": [
        {
          "internalType": "uint256",
          "name": "",
          "type": "uint256"
        }
      ],
      "stateMutability": "view",
      "type": "function"
    },
    {
      "inputs": [],
      "name": "PARTICIPANTS_SHARE_BPS",
      "outputs": [
        {
          "internalType": "uint256",
          "name": "",
          "type": "uint256"
        }
      ],
      "stateMutability": "view",
      "type": "function"
    },
    {
      "inputs": [],
      "name": "PROTOCOL_SHARE_BPS",
      "outputs": [
        {
          "internalType": "uint256",
          "name": "",
          "type": "uint256"
        }
      ],
      "stateMutability": "view",
      "type": "function"
    },
    {
      "inputs": [],
      "name": "SUBMARINE_SIZE",
      "outputs": [
        {
          "internalType": "uint8",
          "name": "",
          "type": "uint8"
        }
      ],
      "stateMutability": "view",
      "type": "function"
    },
    {
      "inputs": [
        {
          "internalType": "uint8",
          "name": "tierId",
          "type": "uint8"
        }
      ],
      "name": "TIER_SIZES",
      "outputs": [
        {
          "internalType": "uint8",
          "name": "",
          "type": "uint8"
        }
      ],
      "stateMutability": "view",
      "type": "function"
    },
    {
      "inputs": [],
      "name": "TOTAL_SHIP_CELLS",
      "outputs": [
        {
          "internalType": "uint8",
          "name": "",
          "type": "uint8"
        }
      ],
      "stateMutability": "view",
      "type": "function"
    },
    {
      "inputs": [
        {
          "internalType": "bytes32",
          "name": "",
          "type": "bytes32"
        }
      ],
      "name": "cacheKeyToIndex",
      "outputs": [
        {
          "internalType": "uint16",
          "name": "",
          "type": "uint16"
        }
      ],
      "stateMutability": "view",
      "type": "function"
    },
    {
      "inputs": [
        {
          "internalType": "uint8",
          "name": "tierId",
          "type": "uint8"
        },
        {
          "internalType": "uint8",
          "name": "instanceId",
          "type": "uint8"
        }
      ],
      "name": "claimAbandonedEnrollmentPool",
      "outputs": [],
      "stateMutability": "nonpayable",
      "type": "function"
    },
    {
      "inputs": [
        {
          "internalType": "uint8",
          "name": "tierId",
          "type": "uint8"
        },
        {
          "internalType": "uint8",
          "name": "instanceId",
          "type": "uint8"
        },
        {
          "internalType": "uint8",
          "name": "roundNumber",
          "type": "uint8"
        },
        {
          "internalType": "uint8",
          "name": "matchNumber",
          "type": "uint8"
        }
      ],
      "name": "claimTimeoutWin",
      "outputs": [],
      "stateMutability": "nonpayable",
      "type": "function"
    },
    {
      "inputs": [
        {
          "internalType": "uint8",
          "name": "tierId",
          "type": "uint8"
        },
        {
          "internalType": "uint8",
          "name": "instanceId",
          "type": "uint8"
        },
        {
          "internalType": "uint8",
          "name": "roundNumber",
          "type": "uint8"
        },
        {
          "internalType": "uint8",
          "name": "matchNumber",
          "type": "uint8"
        },
        {
          "internalType": "bytes32",
          "name": "commitment",
          "type": "bytes32"
        }
      ],
      "name": "commitBoard",
      "outputs": [],
      "stateMutability": "nonpayable",
      "type": "function"
    },
    {
      "inputs": [
        {
          "internalType": "uint256",
          "name": "",
          "type": "uint256"
        }
      ],
      "name": "completedTournaments",
      "outputs": [
        {
          "internalType": "bool",
          "name": "exists",
          "type": "bool"
        },
        {
          "internalType": "uint8",
          "name": "tierId",
          "type": "uint8"
        },
        {
          "internalType": "uint8",
          "name": "instanceId",
          "type": "uint8"
        },
        {
          "internalType": "uint256",
          "name": "tournamentId",
          "type": "uint256"
        },
        {
          "internalType": "uint256",
          "name": "timestamp",
          "type": "uint256"
        },
        {
          "internalType": "enum ETour.Mode",
          "name": "mode",
          "type": "uint8"
        },
        {
          "internalType": "enum ETour.TournamentCompletionType",
          "name": "completionType",
          "type": "uint8"
        },
        {
          "internalType": "uint256",
          "name": "totalPrizePool",
          "type": "uint256"
        },
        {
          "internalType": "uint256",
          "name": "totalAwarded",
          "type": "uint256"
        },
        {
          "internalType": "address",
          "name": "winner",
          "type": "address"
        },
        {
          "internalType": "uint8",
          "name": "participantCount",
          "type": "uint8"
        },
        {
          "internalType": "uint256",
          "name": "startTime",
          "type": "uint256"
        },
        {
          "internalType": "uint256",
          "name": "duration",
          "type": "uint256"
        },
        {
          "internalType": "uint8",
          "name": "matchCount",
          "type": "uint8"
        }
      ],
      "stateMutability": "view",
      "type": "function"
    },
    {
      "inputs": [],
      "name": "declareRW3",
      "outputs": [
        {
          "internalType": "string",
          "name": "",
          "type": "string"
        }
      ],
      "stateMutability": "view",
      "type": "function"
    },
    {
      "inputs": [
        {
          "internalType": "uint8",
          "name": "",
          "type": "uint8"
        },
        {
          "internalType": "uint8",
          "name": "",
          "type": "uint8"
        },
        {
          "internalType": "uint8",
          "name": "",
          "type": "uint8"
        },
        {
          "internalType": "uint8",
          "name": "",
          "type": "uint8"
        },
        {
          "internalType": "address",
          "name": "",
          "type": "address"
        }
      ],
      "name": "drawParticipants",
      "outputs": [
        {
          "internalType": "bool",
          "name": "",
          "type": "bool"
        }
      ],
      "stateMutability": "view",
      "type": "function"
    },
    {
      "inputs": [
        {
          "internalType": "uint8",
          "name": "tierId",
          "type": "uint8"
        },
        {
          "internalType": "uint8",
          "name": "instanceId",
          "type": "uint8"
        }
      ],
      "name": "enrollInTournament",
      "outputs": [],
      "stateMutability": "payable",
      "type": "function"
    },
    {
      "inputs": [
        {
          "internalType": "uint8",
          "name": "",
          "type": "uint8"
        },
        {
          "internalType": "uint8",
          "name": "",
          "type": "uint8"
        },
        {
          "internalType": "uint256",
          "name": "",
          "type": "uint256"
        }
      ],
      "name": "enrolledPlayers",
      "outputs": [
        {
          "internalType": "address",
          "name": "",
          "type": "address"
        }
      ],
      "stateMutability": "view",
      "type": "function"
    },
    {
      "inputs": [
        {
          "internalType": "address",
          "name": "player",
          "type": "address"
        }
      ],
      "name": "findPlayerMatch",
      "outputs": [
        {
          "internalType": "bool",
          "name": "found",
          "type": "bool"
        },
        {
          "internalType": "uint8",
          "name": "tierId",
          "type": "uint8"
        },
        {
          "internalType": "uint8",
          "name": "instanceId",
          "type": "uint8"
        },
        {
          "internalType": "uint8",
          "name": "roundNumber",
          "type": "uint8"
        },
        {
          "internalType": "uint8",
          "name": "matchNumber",
          "type": "uint8"
        },
        {
          "internalType": "enum EternalBattleship.MatchPhase",
          "name": "phase",
          "type": "uint8"
        },
        {
          "internalType": "address",
          "name": "opponent",
          "type": "address"
        },
        {
          "internalType": "bool",
          "name": "isPlayerTurn",
          "type": "bool"
        },
        {
          "internalType": "bool",
          "name": "playerHasCommitted",
          "type": "bool"
        },
        {
          "internalType": "bool",
          "name": "playerHasRevealed",
          "type": "bool"
        },
        {
          "internalType": "bool",
          "name": "opponentHasCommitted",
          "type": "bool"
        },
        {
          "internalType": "bool",
          "name": "opponentHasRevealed",
          "type": "bool"
        }
      ],
      "stateMutability": "view",
      "type": "function"
    },
    {
      "inputs": [
        {
          "internalType": "uint8",
          "name": "tierId",
          "type": "uint8"
        },
        {
          "internalType": "uint8",
          "name": "instanceId",
          "type": "uint8"
        },
        {
          "internalType": "uint8",
          "name": "roundNumber",
          "type": "uint8"
        },
        {
          "internalType": "uint8",
          "name": "matchNumber",
          "type": "uint8"
        },
        {
          "internalType": "uint8",
          "name": "targetCell",
          "type": "uint8"
        }
      ],
      "name": "fireShot",
      "outputs": [],
      "stateMutability": "nonpayable",
      "type": "function"
    },
    {
      "inputs": [
        {
          "internalType": "uint8",
          "name": "tierId",
          "type": "uint8"
        },
        {
          "internalType": "uint8",
          "name": "instanceId",
          "type": "uint8"
        }
      ],
      "name": "forceStartTournament",
      "outputs": [],
      "stateMutability": "nonpayable",
      "type": "function"
    },
    {
      "inputs": [
        {
          "internalType": "uint8[17]",
          "name": "shipPositions",
          "type": "uint8[17]"
        },
        {
          "internalType": "bytes",
          "name": "signature",
          "type": "bytes"
        }
      ],
      "name": "generateCommitment",
      "outputs": [
        {
          "internalType": "bytes32",
          "name": "",
          "type": "bytes32"
        }
      ],
      "stateMutability": "pure",
      "type": "function"
    },
    {
      "inputs": [],
      "name": "getAllCompletedTournaments",
      "outputs": [
        {
          "components": [
            {
              "internalType": "bool",
              "name": "exists",
              "type": "bool"
            },
            {
              "internalType": "uint8",
              "name": "tierId",
              "type": "uint8"
            },
            {
              "internalType": "uint8",
              "name": "instanceId",
              "type": "uint8"
            },
            {
              "internalType": "uint256",
              "name": "tournamentId",
              "type": "uint256"
            },
            {
              "internalType": "uint256",
              "name": "timestamp",
              "type": "uint256"
            },
            {
              "internalType": "enum ETour.Mode",
              "name": "mode",
              "type": "uint8"
            },
            {
              "internalType": "enum ETour.TournamentCompletionType",
              "name": "completionType",
              "type": "uint8"
            },
            {
              "internalType": "uint256",
              "name": "totalPrizePool",
              "type": "uint256"
            },
            {
              "internalType": "uint256",
              "name": "totalAwarded",
              "type": "uint256"
            },
            {
              "internalType": "address",
              "name": "winner",
              "type": "address"
            },
            {
              "internalType": "uint8",
              "name": "participantCount",
              "type": "uint8"
            },
            {
              "internalType": "uint256",
              "name": "startTime",
              "type": "uint256"
            },
            {
              "internalType": "uint256",
              "name": "duration",
              "type": "uint256"
            },
            {
              "internalType": "uint8",
              "name": "matchCount",
              "type": "uint8"
            },
            {
              "components": [
                {
                  "internalType": "address",
                  "name": "player",
                  "type": "address"
                },
                {
                  "internalType": "uint8",
                  "name": "ranking",
                  "type": "uint8"
                },
                {
                  "internalType": "uint256",
                  "name": "prize",
                  "type": "uint256"
                }
              ],
              "internalType": "struct ETour.PrizeWinner[]",
              "name": "prizeWinners",
              "type": "tuple[]"
            }
          ],
          "internalType": "struct ETour.CachedTournamentData[]",
          "name": "",
          "type": "tuple[]"
        }
      ],
      "stateMutability": "view",
      "type": "function"
    },
    {
      "inputs": [
        {
          "internalType": "uint16",
          "name": "index",
          "type": "uint16"
        }
      ],
      "name": "getCachedMatchByIndex",
      "outputs": [
        {
          "components": [
            {
              "internalType": "address",
              "name": "player1",
              "type": "address"
            },
            {
              "internalType": "address",
              "name": "player2",
              "type": "address"
            },
            {
              "internalType": "address",
              "name": "winner",
              "type": "address"
            },
            {
              "internalType": "uint256",
              "name": "startTime",
              "type": "uint256"
            },
            {
              "internalType": "uint256",
              "name": "endTime",
              "type": "uint256"
            },
            {
              "internalType": "uint8",
              "name": "tierId",
              "type": "uint8"
            },
            {
              "internalType": "uint8",
              "name": "instanceId",
              "type": "uint8"
            },
            {
              "internalType": "uint8",
              "name": "roundNumber",
              "type": "uint8"
            },
            {
              "internalType": "uint8",
              "name": "matchNumber",
              "type": "uint8"
            },
            {
              "internalType": "bool",
              "name": "exists",
              "type": "bool"
            },
            {
              "internalType": "uint8",
              "name": "player1ShotsHit",
              "type": "uint8"
            },
            {
              "internalType": "uint8",
              "name": "player2ShotsHit",
              "type": "uint8"
            }
          ],
          "internalType": "struct EternalBattleship.CachedBattleshipMatch",
          "name": "",
          "type": "tuple"
        }
      ],
      "stateMutability": "view",
      "type": "function"
    },
    {
      "inputs": [
        {
          "internalType": "uint8",
          "name": "tierId",
          "type": "uint8"
        },
        {
          "internalType": "uint8",
          "name": "instanceId",
          "type": "uint8"
        },
        {
          "internalType": "address",
          "name": "player",
          "type": "address"
        }
      ],
      "name": "getCommitMessage",
      "outputs": [
        {
          "internalType": "bytes32",
          "name": "",
          "type": "bytes32"
        }
      ],
      "stateMutability": "pure",
      "type": "function"
    },
    {
      "inputs": [
        {
          "internalType": "uint256",
          "name": "index",
          "type": "uint256"
        }
      ],
      "name": "getCompletedTournament",
      "outputs": [
        {
          "components": [
            {
              "internalType": "bool",
              "name": "exists",
              "type": "bool"
            },
            {
              "internalType": "uint8",
              "name": "tierId",
              "type": "uint8"
            },
            {
              "internalType": "uint8",
              "name": "instanceId",
              "type": "uint8"
            },
            {
              "internalType": "uint256",
              "name": "tournamentId",
              "type": "uint256"
            },
            {
              "internalType": "uint256",
              "name": "timestamp",
              "type": "uint256"
            },
            {
              "internalType": "enum ETour.Mode",
              "name": "mode",
              "type": "uint8"
            },
            {
              "internalType": "enum ETour.TournamentCompletionType",
              "name": "completionType",
              "type": "uint8"
            },
            {
              "internalType": "uint256",
              "name": "totalPrizePool",
              "type": "uint256"
            },
            {
              "internalType": "uint256",
              "name": "totalAwarded",
              "type": "uint256"
            },
            {
              "internalType": "address",
              "name": "winner",
              "type": "address"
            },
            {
              "internalType": "uint8",
              "name": "participantCount",
              "type": "uint8"
            },
            {
              "internalType": "uint256",
              "name": "startTime",
              "type": "uint256"
            },
            {
              "internalType": "uint256",
              "name": "duration",
              "type": "uint256"
            },
            {
              "internalType": "uint8",
              "name": "matchCount",
              "type": "uint8"
            },
            {
              "components": [
                {
                  "internalType": "address",
                  "name": "player",
                  "type": "address"
                },
                {
                  "internalType": "uint8",
                  "name": "ranking",
                  "type": "uint8"
                },
                {
                  "internalType": "uint256",
                  "name": "prize",
                  "type": "uint256"
                }
              ],
              "internalType": "struct ETour.PrizeWinner[]",
              "name": "prizeWinners",
              "type": "tuple[]"
            }
          ],
          "internalType": "struct ETour.CachedTournamentData",
          "name": "",
          "type": "tuple"
        }
      ],
      "stateMutability": "view",
      "type": "function"
    },
    {
      "inputs": [],
      "name": "getCompletedTournamentCount",
      "outputs": [
        {
          "internalType": "uint256",
          "name": "",
          "type": "uint256"
        }
      ],
      "stateMutability": "view",
      "type": "function"
    },
    {
      "inputs": [
        {
          "internalType": "uint8",
          "name": "tierId",
          "type": "uint8"
        },
        {
          "internalType": "uint8",
          "name": "instanceId",
          "type": "uint8"
        }
      ],
      "name": "getEnrolledPlayers",
      "outputs": [
        {
          "internalType": "address[]",
          "name": "",
          "type": "address[]"
        }
      ],
      "stateMutability": "view",
      "type": "function"
    },
    {
      "inputs": [
        {
          "internalType": "bytes32",
          "name": "matchId",
          "type": "bytes32"
        }
      ],
      "name": "getMatchCoordinates",
      "outputs": [
        {
          "internalType": "bool",
          "name": "exists",
          "type": "bool"
        },
        {
          "internalType": "uint8",
          "name": "tierId",
          "type": "uint8"
        },
        {
          "internalType": "uint8",
          "name": "instanceId",
          "type": "uint8"
        },
        {
          "internalType": "uint8",
          "name": "roundNumber",
          "type": "uint8"
        },
        {
          "internalType": "uint8",
          "name": "matchNumber",
          "type": "uint8"
        }
      ],
      "stateMutability": "view",
      "type": "function"
    },
    {
      "inputs": [
        {
          "internalType": "uint8",
          "name": "tierId",
          "type": "uint8"
        },
        {
          "internalType": "uint8",
          "name": "instanceId",
          "type": "uint8"
        },
        {
          "internalType": "uint8",
          "name": "roundNumber",
          "type": "uint8"
        },
        {
          "internalType": "uint8",
          "name": "matchNumber",
          "type": "uint8"
        }
      ],
      "name": "getMatchState",
      "outputs": [
        {
          "internalType": "address",
          "name": "player1",
          "type": "address"
        },
        {
          "internalType": "address",
          "name": "player2",
          "type": "address"
        },
        {
          "internalType": "address",
          "name": "currentTurn",
          "type": "address"
        },
        {
          "internalType": "address",
          "name": "winner",
          "type": "address"
        },
        {
          "internalType": "enum ETour.MatchStatus",
          "name": "status",
          "type": "uint8"
        },
        {
          "internalType": "enum EternalBattleship.MatchPhase",
          "name": "phase",
          "type": "uint8"
        },
        {
          "internalType": "bool",
          "name": "player1Committed",
          "type": "bool"
        },
        {
          "internalType": "bool",
          "name": "player2Committed",
          "type": "bool"
        },
        {
          "internalType": "bool",
          "name": "player1Revealed",
          "type": "bool"
        },
        {
          "internalType": "bool",
          "name": "player2Revealed",
          "type": "bool"
        },
        {
          "internalType": "uint8",
          "name": "player1ShipsRemaining",
          "type": "uint8"
        },
        {
          "internalType": "uint8",
          "name": "player2ShipsRemaining",
          "type": "uint8"
        }
      ],
      "stateMutability": "view",
      "type": "function"
    },
    {
      "inputs": [
        {
          "internalType": "uint8",
          "name": "tierId",
          "type": "uint8"
        },
        {
          "internalType": "uint8",
          "name": "instanceId",
          "type": "uint8"
        },
        {
          "internalType": "uint8",
          "name": "roundNumber",
          "type": "uint8"
        },
        {
          "internalType": "uint8",
          "name": "matchNumber",
          "type": "uint8"
        }
      ],
      "name": "getMyBoard",
      "outputs": [
        {
          "internalType": "enum EternalBattleship.CellState[100]",
          "name": "",
          "type": "uint8[100]"
        }
      ],
      "stateMutability": "view",
      "type": "function"
    },
    {
      "inputs": [
        {
          "internalType": "uint8",
          "name": "tierId",
          "type": "uint8"
        },
        {
          "internalType": "uint8",
          "name": "instanceId",
          "type": "uint8"
        },
        {
          "internalType": "uint8",
          "name": "roundNumber",
          "type": "uint8"
        },
        {
          "internalType": "uint8",
          "name": "matchNumber",
          "type": "uint8"
        }
      ],
      "name": "getOpponentBoard",
      "outputs": [
        {
          "internalType": "enum EternalBattleship.CellState[100]",
          "name": "fogBoard",
          "type": "uint8[100]"
        }
      ],
      "stateMutability": "view",
      "type": "function"
    },
    {
      "inputs": [
        {
          "internalType": "address",
          "name": "player",
          "type": "address"
        }
      ],
      "name": "getPlayerActiveMatches",
      "outputs": [
        {
          "internalType": "bytes32[]",
          "name": "",
          "type": "bytes32[]"
        }
      ],
      "stateMutability": "view",
      "type": "function"
    },
    {
      "inputs": [
        {
          "internalType": "address",
          "name": "player",
          "type": "address"
        }
      ],
      "name": "getPlayerStats",
      "outputs": [
        {
          "internalType": "uint256",
          "name": "tournamentsWon",
          "type": "uint256"
        },
        {
          "internalType": "uint256",
          "name": "tournamentsPlayed",
          "type": "uint256"
        },
        {
          "internalType": "uint256",
          "name": "matchesWon",
          "type": "uint256"
        },
        {
          "internalType": "uint256",
          "name": "matchesPlayed",
          "type": "uint256"
        }
      ],
      "stateMutability": "view",
      "type": "function"
    },
    {
      "inputs": [
        {
          "internalType": "uint8",
          "name": "tierId",
          "type": "uint8"
        },
        {
          "internalType": "uint8",
          "name": "ranking",
          "type": "uint8"
        }
      ],
      "name": "getPrizePercentage",
      "outputs": [
        {
          "internalType": "uint8",
          "name": "percentage",
          "type": "uint8"
        }
      ],
      "stateMutability": "view",
      "type": "function"
    },
    {
      "inputs": [
        {
          "internalType": "uint16",
          "name": "count",
          "type": "uint16"
        }
      ],
      "name": "getRecentCachedMatches",
      "outputs": [
        {
          "components": [
            {
              "internalType": "address",
              "name": "player1",
              "type": "address"
            },
            {
              "internalType": "address",
              "name": "player2",
              "type": "address"
            },
            {
              "internalType": "address",
              "name": "winner",
              "type": "address"
            },
            {
              "internalType": "uint256",
              "name": "startTime",
              "type": "uint256"
            },
            {
              "internalType": "uint256",
              "name": "endTime",
              "type": "uint256"
            },
            {
              "internalType": "uint8",
              "name": "tierId",
              "type": "uint8"
            },
            {
              "internalType": "uint8",
              "name": "instanceId",
              "type": "uint8"
            },
            {
              "internalType": "uint8",
              "name": "roundNumber",
              "type": "uint8"
            },
            {
              "internalType": "uint8",
              "name": "matchNumber",
              "type": "uint8"
            },
            {
              "internalType": "bool",
              "name": "exists",
              "type": "bool"
            },
            {
              "internalType": "uint8",
              "name": "player1ShotsHit",
              "type": "uint8"
            },
            {
              "internalType": "uint8",
              "name": "player2ShotsHit",
              "type": "uint8"
            }
          ],
          "internalType": "struct EternalBattleship.CachedBattleshipMatch[]",
          "name": "recentMatches",
          "type": "tuple[]"
        }
      ],
      "stateMutability": "view",
      "type": "function"
    },
    {
      "inputs": [
        {
          "internalType": "uint8",
          "name": "tierId",
          "type": "uint8"
        },
        {
          "internalType": "uint8",
          "name": "instanceId",
          "type": "uint8"
        },
        {
          "internalType": "uint8",
          "name": "roundNumber",
          "type": "uint8"
        }
      ],
      "name": "getRoundInfo",
      "outputs": [
        {
          "internalType": "uint8",
          "name": "totalMatches",
          "type": "uint8"
        },
        {
          "internalType": "uint8",
          "name": "completedMatches",
          "type": "uint8"
        },
        {
          "internalType": "bool",
          "name": "initialized",
          "type": "bool"
        }
      ],
      "stateMutability": "view",
      "type": "function"
    },
    {
      "inputs": [
        {
          "internalType": "uint8",
          "name": "tierId",
          "type": "uint8"
        },
        {
          "internalType": "uint8",
          "name": "instanceId",
          "type": "uint8"
        },
        {
          "internalType": "uint8",
          "name": "roundNumber",
          "type": "uint8"
        },
        {
          "internalType": "uint8",
          "name": "matchNumber",
          "type": "uint8"
        },
        {
          "internalType": "address",
          "name": "player",
          "type": "address"
        }
      ],
      "name": "getShotsReceivedBy",
      "outputs": [
        {
          "internalType": "bool[100]",
          "name": "",
          "type": "bool[100]"
        }
      ],
      "stateMutability": "view",
      "type": "function"
    },
    {
      "inputs": [
        {
          "internalType": "uint8",
          "name": "tierId",
          "type": "uint8"
        }
      ],
      "name": "getTierOverview",
      "outputs": [
        {
          "internalType": "enum ETour.TournamentStatus[]",
          "name": "statuses",
          "type": "uint8[]"
        },
        {
          "internalType": "uint8[]",
          "name": "enrolledCounts",
          "type": "uint8[]"
        },
        {
          "internalType": "uint256[]",
          "name": "prizePools",
          "type": "uint256[]"
        }
      ],
      "stateMutability": "view",
      "type": "function"
    },
    {
      "inputs": [
        {
          "internalType": "uint8",
          "name": "tierId",
          "type": "uint8"
        }
      ],
      "name": "getTierPrizeDistribution",
      "outputs": [
        {
          "internalType": "uint8[]",
          "name": "percentages",
          "type": "uint8[]"
        }
      ],
      "stateMutability": "view",
      "type": "function"
    },
    {
      "inputs": [
        {
          "internalType": "uint8",
          "name": "tierId",
          "type": "uint8"
        },
        {
          "internalType": "uint8",
          "name": "instanceId",
          "type": "uint8"
        }
      ],
      "name": "getTournamentInfo",
      "outputs": [
        {
          "internalType": "enum ETour.TournamentStatus",
          "name": "status",
          "type": "uint8"
        },
        {
          "internalType": "enum ETour.Mode",
          "name": "mode",
          "type": "uint8"
        },
        {
          "internalType": "uint8",
          "name": "currentRound",
          "type": "uint8"
        },
        {
          "internalType": "uint8",
          "name": "enrolledCount",
          "type": "uint8"
        },
        {
          "internalType": "uint256",
          "name": "prizePool",
          "type": "uint256"
        },
        {
          "internalType": "address",
          "name": "winner",
          "type": "address"
        }
      ],
      "stateMutability": "view",
      "type": "function"
    },
    {
      "inputs": [],
      "name": "globalTournamentIdCounter",
      "outputs": [
        {
          "internalType": "uint256",
          "name": "",
          "type": "uint256"
        }
      ],
      "stateMutability": "view",
      "type": "function"
    },
    {
      "inputs": [
        {
          "internalType": "uint8",
          "name": "",
          "type": "uint8"
        },
        {
          "internalType": "uint8",
          "name": "",
          "type": "uint8"
        },
        {
          "internalType": "address",
          "name": "",
          "type": "address"
        }
      ],
      "name": "isEnrolled",
      "outputs": [
        {
          "internalType": "bool",
          "name": "",
          "type": "bool"
        }
      ],
      "stateMutability": "view",
      "type": "function"
    },
    {
      "inputs": [
        {
          "internalType": "uint256",
          "name": "",
          "type": "uint256"
        }
      ],
      "name": "matchCache",
      "outputs": [
        {
          "internalType": "address",
          "name": "player1",
          "type": "address"
        },
        {
          "internalType": "address",
          "name": "player2",
          "type": "address"
        },
        {
          "internalType": "address",
          "name": "winner",
          "type": "address"
        },
        {
          "internalType": "uint256",
          "name": "startTime",
          "type": "uint256"
        },
        {
          "internalType": "uint256",
          "name": "endTime",
          "type": "uint256"
        },
        {
          "internalType": "uint8",
          "name": "tierId",
          "type": "uint8"
        },
        {
          "internalType": "uint8",
          "name": "instanceId",
          "type": "uint8"
        },
        {
          "internalType": "uint8",
          "name": "roundNumber",
          "type": "uint8"
        },
        {
          "internalType": "uint8",
          "name": "matchNumber",
          "type": "uint8"
        },
        {
          "internalType": "bool",
          "name": "exists",
          "type": "bool"
        },
        {
          "internalType": "uint8",
          "name": "player1ShotsHit",
          "type": "uint8"
        },
        {
          "internalType": "uint8",
          "name": "player2ShotsHit",
          "type": "uint8"
        }
      ],
      "stateMutability": "view",
      "type": "function"
    },
    {
      "inputs": [
        {
          "internalType": "bytes32",
          "name": "",
          "type": "bytes32"
        }
      ],
      "name": "matchCoordinates",
      "outputs": [
        {
          "internalType": "uint8",
          "name": "tierId",
          "type": "uint8"
        },
        {
          "internalType": "uint8",
          "name": "instanceId",
          "type": "uint8"
        },
        {
          "internalType": "uint8",
          "name": "roundNumber",
          "type": "uint8"
        },
        {
          "internalType": "uint8",
          "name": "matchNumber",
          "type": "uint8"
        },
        {
          "internalType": "bool",
          "name": "exists",
          "type": "bool"
        }
      ],
      "stateMutability": "view",
      "type": "function"
    },
    {
      "inputs": [],
      "name": "nextCacheIndex",
      "outputs": [
        {
          "internalType": "uint16",
          "name": "",
          "type": "uint16"
        }
      ],
      "stateMutability": "view",
      "type": "function"
    },
    {
      "inputs": [],
      "name": "owner",
      "outputs": [
        {
          "internalType": "address",
          "name": "",
          "type": "address"
        }
      ],
      "stateMutability": "view",
      "type": "function"
    },
    {
      "inputs": [
        {
          "internalType": "address",
          "name": "",
          "type": "address"
        },
        {
          "internalType": "uint256",
          "name": "",
          "type": "uint256"
        }
      ],
      "name": "playerActiveMatches",
      "outputs": [
        {
          "internalType": "bytes32",
          "name": "",
          "type": "bytes32"
        }
      ],
      "stateMutability": "view",
      "type": "function"
    },
    {
      "inputs": [
        {
          "internalType": "uint8",
          "name": "",
          "type": "uint8"
        },
        {
          "internalType": "uint8",
          "name": "",
          "type": "uint8"
        },
        {
          "internalType": "address",
          "name": "",
          "type": "address"
        }
      ],
      "name": "playerForfeitedAmounts",
      "outputs": [
        {
          "internalType": "uint256",
          "name": "",
          "type": "uint256"
        }
      ],
      "stateMutability": "view",
      "type": "function"
    },
    {
      "inputs": [
        {
          "internalType": "address",
          "name": "",
          "type": "address"
        },
        {
          "internalType": "bytes32",
          "name": "",
          "type": "bytes32"
        }
      ],
      "name": "playerMatchIndex",
      "outputs": [
        {
          "internalType": "uint256",
          "name": "",
          "type": "uint256"
        }
      ],
      "stateMutability": "view",
      "type": "function"
    },
    {
      "inputs": [
        {
          "internalType": "uint8",
          "name": "",
          "type": "uint8"
        },
        {
          "internalType": "uint8",
          "name": "",
          "type": "uint8"
        },
        {
          "internalType": "address",
          "name": "",
          "type": "address"
        }
      ],
      "name": "playerPrizes",
      "outputs": [
        {
          "internalType": "uint256",
          "name": "",
          "type": "uint256"
        }
      ],
      "stateMutability": "view",
      "type": "function"
    },
    {
      "inputs": [
        {
          "internalType": "uint8",
          "name": "",
          "type": "uint8"
        },
        {
          "internalType": "uint8",
          "name": "",
          "type": "uint8"
        },
        {
          "internalType": "address",
          "name": "",
          "type": "address"
        }
      ],
      "name": "playerRanking",
      "outputs": [
        {
          "internalType": "uint8",
          "name": "",
          "type": "uint8"
        }
      ],
      "stateMutability": "view",
      "type": "function"
    },
    {
      "inputs": [
        {
          "internalType": "address",
          "name": "",
          "type": "address"
        }
      ],
      "name": "playerStats",
      "outputs": [
        {
          "internalType": "uint256",
          "name": "tournamentsWon",
          "type": "uint256"
        },
        {
          "internalType": "uint256",
          "name": "tournamentsPlayed",
          "type": "uint256"
        },
        {
          "internalType": "uint256",
          "name": "matchesWon",
          "type": "uint256"
        },
        {
          "internalType": "uint256",
          "name": "matchesPlayed",
          "type": "uint256"
        }
      ],
      "stateMutability": "view",
      "type": "function"
    },
    {
      "inputs": [
        {
          "internalType": "uint8",
          "name": "tierId",
          "type": "uint8"
        },
        {
          "internalType": "uint8",
          "name": "instanceId",
          "type": "uint8"
        },
        {
          "internalType": "uint8",
          "name": "roundNumber",
          "type": "uint8"
        },
        {
          "internalType": "uint8",
          "name": "matchNumber",
          "type": "uint8"
        },
        {
          "internalType": "uint8",
          "name": "cellIndex",
          "type": "uint8"
        }
      ],
      "name": "queryOpponentCell",
      "outputs": [
        {
          "internalType": "enum EternalBattleship.CellState",
          "name": "",
          "type": "uint8"
        }
      ],
      "stateMutability": "view",
      "type": "function"
    },
    {
      "inputs": [
        {
          "internalType": "uint8",
          "name": "tierId",
          "type": "uint8"
        },
        {
          "internalType": "uint8",
          "name": "instanceId",
          "type": "uint8"
        },
        {
          "internalType": "uint8",
          "name": "roundNumber",
          "type": "uint8"
        },
        {
          "internalType": "uint8",
          "name": "matchNumber",
          "type": "uint8"
        },
        {
          "internalType": "uint8[17]",
          "name": "shipPositions",
          "type": "uint8[17]"
        },
        {
          "internalType": "bytes",
          "name": "signature",
          "type": "bytes"
        }
      ],
      "name": "revealBoard",
      "outputs": [],
      "stateMutability": "nonpayable",
      "type": "function"
    },
    {
      "inputs": [
        {
          "internalType": "uint8",
          "name": "",
          "type": "uint8"
        },
        {
          "internalType": "uint8",
          "name": "",
          "type": "uint8"
        },
        {
          "internalType": "uint8",
          "name": "",
          "type": "uint8"
        }
      ],
      "name": "rounds",
      "outputs": [
        {
          "internalType": "uint8",
          "name": "totalMatches",
          "type": "uint8"
        },
        {
          "internalType": "uint8",
          "name": "completedMatches",
          "type": "uint8"
        },
        {
          "internalType": "bool",
          "name": "initialized",
          "type": "bool"
        },
        {
          "internalType": "uint8",
          "name": "drawCount",
          "type": "uint8"
        },
        {
          "internalType": "bool",
          "name": "allMatchesDrew",
          "type": "bool"
        }
      ],
      "stateMutability": "view",
      "type": "function"
    },
    {
      "inputs": [
        {
          "internalType": "uint8",
          "name": "tierId",
          "type": "uint8"
        }
      ],
      "name": "tierConfigs",
      "outputs": [
        {
          "internalType": "uint8",
          "name": "playerCount",
          "type": "uint8"
        },
        {
          "internalType": "uint8",
          "name": "instanceCount",
          "type": "uint8"
        },
        {
          "internalType": "uint256",
          "name": "entryFee",
          "type": "uint256"
        },
        {
          "internalType": "uint8",
          "name": "totalRounds",
          "type": "uint8"
        }
      ],
      "stateMutability": "view",
      "type": "function"
    },
    {
      "inputs": [],
      "name": "tierCount",
      "outputs": [
        {
          "internalType": "uint8",
          "name": "",
          "type": "uint8"
        }
      ],
      "stateMutability": "view",
      "type": "function"
    },
    {
      "inputs": [
        {
          "internalType": "uint256",
          "name": "",
          "type": "uint256"
        }
      ],
      "name": "tournamentCompletionBlocks",
      "outputs": [
        {
          "internalType": "uint256",
          "name": "",
          "type": "uint256"
        }
      ],
      "stateMutability": "view",
      "type": "function"
    },
    {
      "inputs": [
        {
          "internalType": "uint8",
          "name": "",
          "type": "uint8"
        },
        {
          "internalType": "uint8",
          "name": "",
          "type": "uint8"
        }
      ],
      "name": "tournaments",
      "outputs": [
        {
          "internalType": "uint8",
          "name": "tierId",
          "type": "uint8"
        },
        {
          "internalType": "uint8",
          "name": "instanceId",
          "type": "uint8"
        },
        {
          "internalType": "enum ETour.TournamentStatus",
          "name": "status",
          "type": "uint8"
        },
        {
          "internalType": "enum ETour.Mode",
          "name": "mode",
          "type": "uint8"
        },
        {
          "internalType": "uint8",
          "name": "currentRound",
          "type": "uint8"
        },
        {
          "internalType": "uint8",
          "name": "enrolledCount",
          "type": "uint8"
        },
        {
          "internalType": "uint256",
          "name": "prizePool",
          "type": "uint256"
        },
        {
          "internalType": "uint256",
          "name": "startTime",
          "type": "uint256"
        },
        {
          "internalType": "address",
          "name": "winner",
          "type": "address"
        },
        {
          "internalType": "address",
          "name": "coWinner",
          "type": "address"
        },
        {
          "internalType": "bool",
          "name": "finalsWasDraw",
          "type": "bool"
        },
        {
          "internalType": "bool",
          "name": "allDrawResolution",
          "type": "bool"
        },
        {
          "internalType": "uint8",
          "name": "allDrawRound",
          "type": "uint8"
        },
        {
          "components": [
            {
              "internalType": "uint256",
              "name": "escalation1Start",
              "type": "uint256"
            },
            {
              "internalType": "uint256",
              "name": "escalation2Start",
              "type": "uint256"
            },
            {
              "internalType": "enum ETour.EscalationLevel",
              "name": "activeEscalation",
              "type": "uint8"
            },
            {
              "internalType": "uint256",
              "name": "forfeitPool",
              "type": "uint256"
            }
          ],
          "internalType": "struct ETour.EnrollmentTimeoutState",
          "name": "enrollmentTimeout",
          "type": "tuple"
        },
        {
          "internalType": "bool",
          "name": "hasStartedViaTimeout",
          "type": "bool"
        },
        {
          "internalType": "address",
          "name": "firstEnroller",
          "type": "address"
        },
        {
          "internalType": "uint256",
          "name": "firstEnrollmentTimestamp",
          "type": "uint256"
        },
        {
          "internalType": "address",
          "name": "forceStarter",
          "type": "address"
        },
        {
          "internalType": "uint256",
          "name": "forceStartTimestamp",
          "type": "uint256"
        }
      ],
      "stateMutability": "view",
      "type": "function"
    },
    {
      "inputs": [
        {
          "internalType": "bytes32",
          "name": "messageHash",
          "type": "bytes32"
        },
        {
          "internalType": "bytes",
          "name": "signature",
          "type": "bytes"
        },
        {
          "internalType": "address",
          "name": "expectedSigner",
          "type": "address"
        }
      ],
      "name": "verifySignature",
      "outputs": [
        {
          "internalType": "bool",
          "name": "",
          "type": "bool"
        }
      ],
      "stateMutability": "pure",
      "type": "function"
    }
  ]